awsglueavailability/__init__.py
awsglueavailability/__main__.py
awsglueavailability/app.py
awsglueavailability/client.py
awsglueavailability-0.1.1.dist-info/METADATA
awsglueavailability-0.1.1.dist-info/WHEEL
awsglueavailability-0.1.1.dist-info/RECORD
