Metadata-Version: 2.1
Name: awsglueavailability
Version: 0.1.1
Summary: 
Author: Jon Paske
Author-email: joncpaske@gmail.com
Requires-Python: >=3.13,<4.0
Classifier: Programming Language :: Python :: 3
Classifier: Programming Language :: Python :: 3.13
Requires-Dist: boto3 (>=1.38.30,<2.0.0)
Requires-Dist: diagrams (>=0.24.4,<0.25.0)
